modify_csi_datatable/__init__.py
modify_csi_datatable/cli.py
modify_csi_datatable/flask_ui.py
modify_csi_datatable/modify_cfg_file.py
modify_csi_datatable/modify_csi_datatable.py
modify_csi_datatable/utils.py
modify_csi_datatable-1.0.1.dist-info/DESCRIPTION.rst
modify_csi_datatable-1.0.1.dist-info/METADATA
modify_csi_datatable-1.0.1.dist-info/RECORD
modify_csi_datatable-1.0.1.dist-info/WHEEL
modify_csi_datatable-1.0.1.dist-info/metadata.json
modify_csi_datatable-1.0.1.dist-info/top_level.txt
test/__init__.py
test/test_cfg_file_update.py
test/test_datatable_interval.py
test/test_datatable_name.py
test/test_flask.py
