Metadata-Version: 2.0
Name: modify-csi-datatable
Version: 1.0.1
Summary: Utility to allow the quick change of the datatable name and interval in a Draker CRBasic program
Home-page: https://code.draker.us/engineering/modify_csi_datatable
Author: Joe Eastman
Author-email: joe.eastman@drakerenergy.com
License: GNU GPLv3
